{
  "problems": [
    {
      "type": "numerical",
      "question": "A ball is thrown upward with an initial velocity of {v0} m/s. How high does it go? (Ignore air resistance)",
      "variables": [
        {
          "name": "v0",
          "min": 10,
          "max": 50
        }
      ]
    },
    {
      "type": "multiple-choice",
      "question": "Which of the following is NOT a fundamental force in nature?",
      "choices": [
        "Gravity",
        "Electromagnetism",
        "Strong nuclear force",
        "Weak nuclear force",
        "Centrifugal force"
      ]
    },
    {
      "type": "numerical",
      "question": "A {mass} kg object experiences a force of {force} N. What is its acceleration?",
      "variables": [
        {
          "name": "mass",
          "min": 1,
          "max": 10
        },
        {
          "name": "force",
          "min": 5,
          "max": 50
        }
      ]
    }
  ]
}
